neurodecode/__init__.py
neurodecode/colorer.py
neurodecode/pycnbi_config.py
neurodecode/analysis/__init__.py
neurodecode/analysis/feature_importances_topo.py
neurodecode/analysis/parse_features.py
neurodecode/analysis/tfr_export.py
neurodecode/analysis/tfr_export_each_file.py
neurodecode/decoder/__init__.py
neurodecode/decoder/decoder.py
neurodecode/decoder/features.py
neurodecode/decoder/rlda.py
neurodecode/decoder/trainer.py
neurodecode/glass/__init__.py
neurodecode/glass/bgi_client.py
neurodecode/protocols/__init__.py
neurodecode/protocols/feedback.py
neurodecode/protocols/feedback_fes.py
neurodecode/protocols/viz_bars.py
neurodecode/protocols/viz_images.py
neurodecode/stream_player/__init__.py
neurodecode/stream_player/stream_player.py
neurodecode/stream_receiver/__init__.py
neurodecode/stream_receiver/stream_receiver.py
neurodecode/stream_recorder/__init__.py
neurodecode/stream_recorder/stream_recorder.py
neurodecode/stream_viewer/__init__.py
neurodecode/stream_viewer/scope_settings.ini
neurodecode/stream_viewer/stream_viewer.py
neurodecode/stream_viewer/ui_mainwindow_Viewer.py
neurodecode/triggers/__init__.py
neurodecode/triggers/pyLptControl.py
neurodecode/triggers/trigger_def.py
neurodecode/utils/Motionstim8.py
neurodecode/utils/ScalerMad.py
neurodecode/utils/__init__.py
neurodecode/utils/add_lsl_events.py
neurodecode/utils/benchmark_decoder.py
neurodecode/utils/benchmark_multitaper.py
neurodecode/utils/convert2fif.py
neurodecode/utils/epochs2mat.py
neurodecode/utils/epochs2txt.py
neurodecode/utils/fif2mat.py
neurodecode/utils/fif_info.py
neurodecode/utils/fif_resample.py
neurodecode/utils/fix_channel_names.py
neurodecode/utils/hdf5_to_python.py
neurodecode/utils/images2pkl.py
neurodecode/utils/list_trigger_pins.py
neurodecode/utils/mat2fif.py
neurodecode/utils/merge_events.py
neurodecode/utils/nd_lsl.py
neurodecode/utils/parse_online_results.py
neurodecode/utils/psd_visualizer.py
neurodecode/utils/pycnbi_utils.py
neurodecode/utils/q_common.py
neurodecode-2.0.6.dist-info/METADATA
neurodecode-2.0.6.dist-info/WHEEL
neurodecode-2.0.6.dist-info/entry_points.txt
neurodecode-2.0.6.dist-info/top_level.txt
neurodecode-2.0.6.dist-info/RECORD
