Metadata-Version: 2.1
Name: neurodecode
Version: 2.0.6
Summary: Real-time brain signal decoding framework
Home-page: https://github.com/dbdq/neurodecode/
Author: Kyuhwa Lee, Arnaud Desvachez
Author-email: lee.kyuh@gmail.com, arnaud.desvachez@gmail.com
License: The GNU General Public License
Requires-Dist: h5py >=2.7
Requires-Dist: opencv-python >=3.4
Requires-Dist: numpy >=1.16
Requires-Dist: scipy >=1.2
Requires-Dist: colorama >=0.3.9
Requires-Dist: xgboost >=0.81
Requires-Dist: matplotlib >=3.0.2
Requires-Dist: mne >=0.16
Requires-Dist: psutil >=5.4.8
Requires-Dist: setuptools >=39.0.1
Requires-Dist: pyqtgraph >=0.13
Requires-Dist: pylsl >=1.12.2
Requires-Dist: ipython >=6
Requires-Dist: PyQt5 >=5
Requires-Dist: pyxdf >=1.15.2
Requires-Dist: pyserial >=3.4
Requires-Dist: simplejson >=3.16.0
Requires-Dist: scikit-learn >=0.21
Requires-Dist: future
Requires-Dist: configparser
Requires-Dist: lightgbm >=2.3
Requires-Dist: mat73
